person_linkage_case_study/01_generate_pseudopeople_simulated_datasets.ipynb
person_linkage_case_study/02_generate_case_study_files.ipynb
person_linkage_case_study/03_link_datasets.ipynb
person_linkage_case_study/04_calculate_ground_truth_accuracy.ipynb
person_linkage_case_study/LICENSE
person_linkage_case_study/README.md
person_linkage_case_study/Snakefile
person_linkage_case_study/conda.lock.txt
person_linkage_case_study/pip.lock-dask.txt
person_linkage_case_study/pip.lock-dev.txt
person_linkage_case_study/pip.lock-spark.txt
person_linkage_case_study/pip.lock.txt
person_linkage_case_study/setup.py
person_linkage_case_study/benchmarks/benchmark-ri.txt
person_linkage_case_study/benchmarks/benchmark-small_sample.txt
person_linkage_case_study/benchmarks/benchmark-usa.txt
person_linkage_case_study/config/defaults.yaml
person_linkage_case_study/data/fake-names.txt
person_linkage_case_study/diagnostics/executed_notebooks/ri/01_generate_pseudopeople_simulated_datasets.ipynb
person_linkage_case_study/diagnostics/executed_notebooks/ri/02_generate_case_study_files.ipynb
person_linkage_case_study/diagnostics/executed_notebooks/ri/03_link_datasets.ipynb
person_linkage_case_study/diagnostics/executed_notebooks/ri/04_calculate_ground_truth_accuracy.ipynb
person_linkage_case_study/diagnostics/executed_notebooks/small_sample/01_generate_pseudopeople_simulated_datasets.ipynb
person_linkage_case_study/diagnostics/executed_notebooks/small_sample/02_generate_case_study_files.ipynb
person_linkage_case_study/diagnostics/executed_notebooks/small_sample/03_link_datasets.ipynb
person_linkage_case_study/diagnostics/executed_notebooks/small_sample/04_calculate_ground_truth_accuracy.ipynb
person_linkage_case_study/diagnostics/executed_notebooks/usa/01_generate_pseudopeople_simulated_datasets.ipynb
person_linkage_case_study/diagnostics/executed_notebooks/usa/02_generate_case_study_files.ipynb
person_linkage_case_study/diagnostics/executed_notebooks/usa/03_link_datasets.ipynb
person_linkage_case_study-0.1.0.dist-info/LICENSE
person_linkage_case_study-0.1.0.dist-info/METADATA
person_linkage_case_study-0.1.0.dist-info/WHEEL
person_linkage_case_study-0.1.0.dist-info/top_level.txt
person_linkage_case_study-0.1.0.dist-info/RECORD
